payu_sdk/__init__.py
payu_sdk/__test__.py
payu_sdk/payuClient.py
payu_sdk/base/__init__.py
payu_sdk/base/payubase.py
payu_sdk/constants/__init__.py
payu_sdk/constants/payuconstants.py
payu_sdk/errors/__init__.py
payu_sdk/errors/payuerrors.py
payu_sdk/resources/__init__.py
payu_sdk/resources/hasher.py
payu_sdk-1.0.0.dist-info/LICENSE.txt
payu_sdk-1.0.0.dist-info/METADATA
payu_sdk-1.0.0.dist-info/WHEEL
payu_sdk-1.0.0.dist-info/top_level.txt
payu_sdk-1.0.0.dist-info/RECORD
