Metadata-Version: 2.1
Name: payu-sdk
Version: 1.0.0
Summary: PayU Python SDK
Home-page: https://github.com/payu-intrepos/Documentations/wiki/Server-Side
Author: Ashish Kumar
Author-email: dx@payu.in
License: UNKNOWN
Platform: UNKNOWN
Classifier: Programming Language :: Python :: 3
Classifier: License :: OSI Approved :: MIT License
Classifier: Operating System :: OS Independent
